vedro_jj/__init__.py
vedro_jj/_interceptor.py
vedro_jj/_vedro_jj.py
vedro_jj/py.typed
vedro_jj-0.2.0.dist-info/LICENSE
vedro_jj-0.2.0.dist-info/METADATA
vedro_jj-0.2.0.dist-info/WHEEL
vedro_jj-0.2.0.dist-info/top_level.txt
vedro_jj-0.2.0.dist-info/RECORD
