Metadata-Version: 2.1
Name: vedro-jj
Version: 0.2.0
Home-page: https://github.com/vedro-universe/vedro-jj
Author: Nikita Tsvetkov
Author-email: tsv1@fastmail.com
License: Apache-2.0
Project-URL: GitHub, https://github.com/vedro-universe/vedro-jj
Classifier: License :: OSI Approved :: Apache Software License
Classifier: Programming Language :: Python :: 3.8
Classifier: Programming Language :: Python :: 3.9
Classifier: Programming Language :: Python :: 3.10
Classifier: Programming Language :: Python :: 3.11
Classifier: Typing :: Typed
Requires-Python: >=3.8
License-File: LICENSE
Requires-Dist: jj (<3.0,>=2.6)
Requires-Dist: vedro (<2.0,>=1.7)
